Workbook

Sheet Start Here
B2: Restructuring Shareholding Practice Workbook
B3: Built for the IB course, Session 7 (M&A and Restructuring). Practise merger, demerger and composite-scheme shareholding maths.
B5: How to use this workbook
B6: 1. Merger Calc | C6: Any share-swap merger. Enter both companies' shareholders and values. It computes the swap ratio, new shares, cancellations, post-deal ownership and a fairness check.
B7: 2. Demerger Calc | C7: Any demerger. Enter the parent's shareholders and the entitlement ratio (and an optional stake the parent keeps, ITC-style). It computes the new company's ownership, look-through stakes and the ex-price.
B8: 3. Motherson Model | C8: The real deal with real numbers, worked in BOTH orders (demerge then merge vs merge then demerge) side by side.
B9: 4. Practice | C9: 11 problems. Type answers in the YELLOW cells. The Check column says Correct or Try again. Hints are next to each question.
B10: 5. Solutions | C10: Worked answers with live formulas. Look only after you attempt the Practice sheet.
B12: Colour legend
B13: Blue text | C13: Inputs you can change (hardcoded numbers).
B14: Black text | C14: Formulas. Don't overwrite them.
B15: Green text | C15: Formula pulling from another sheet.
B16: Yellow fill | C16: Your answer cells on the Practice sheet.
B18: The five formulas that solve almost every question
B19: Swap ratio | C19: Target value per share ÷ Acquirer value per share
B20: New shares issued | C20: Target shares outstanding × swap ratio
B21: Post-merger shares | C21: Acquirer shares − cancelled cross-holding + new shares
B22: Demerger shares to a holder | C22: Holder's parent shares × (new shares ÷ parent shares) [mirror ownership]
B23: Look-through stake | C23: Direct stake + Σ (stake in each holding company × that company's stake in the business)
B24: Fairness check | C24: Value per share after = (Acquirer value + Target value − value of cancelled shares) ÷ post-merger shares. Unchanged = fair.
B26: Units: shares in millions (mn), values in ₹ crore unless stated. Motherson data is from the 2020 investor presentation, FAQs and valuation reports.

Sheet Merger Calc
B2: Merger Calculator (share swap)
B3: Prefilled with Motherson Step 2 (SAMIL merging into MSSL ex-DWH). Change any blue cell. Shares in mn, values in ₹ per share.
B5: Inputs
B6: Acquirer (surviving company) | C6: MSSL ex-DWH
B7: Target (merging company) | C7: SAMIL
B8: Acquirer value per share (₹) | C8: 101.11
B9: Target value per share (₹) | C9: 516.03
B10: Swap ratio override (leave blank to use values) | C10: 5.1 | H10: Deal ratio 51:10 = 5.1. Delete to use the value-based ratio.
B11: Swap ratio used (acquirer shares per target share) | C11: =IF(C10<>"",C10,IFERROR(C9/C8,0)) -> 5.1
B12: Value-based (fair) ratio | C12: =IFERROR(C9/C8,0) -> 5.1036495
B14: Acquirer shareholders (before)
B15: Holder | C15: Shares (mn) | D15: Held by target? (Y = cancel) | E15: % before
B16: SAMIL | C16: 1055.75 | D16: Y | E16: =IFERROR(C16/$C$22,0) -> 0.33431604
B17: SWS | C17: 800.3 | D17: N | E17: =IFERROR(C17/$C$22,0) -> 0.2534247
B18: Family (direct) | C18: 93.24 | D18: N | E18: =IFERROR(C18/$C$22,0) -> 0.029525577
B19: Public | C19: 1208.65 | D19: N | E19: =IFERROR(C19/$C$22,0) -> 0.38273368
D20: N | E20: =IFERROR(C20/$C$22,0) -> 0
D21: N | E21: =IFERROR(C21/$C$22,0) -> 0
B22: Total | C22: =SUM(C16:C21) -> 3157.94 | E22: =SUM(E16:E21) -> 1
B24: Target shareholders (before)
B25: Holder | C25: Shares (mn) | D25: % before
B26: Family | C26: 428.15 | D26: =IFERROR(C26/$C$31,0) -> 0.90399476
B27: Sojitz + staff | C27: 45.47 | D27: =IFERROR(C27/$C$31,0) -> 0.096005236
D28: =IFERROR(C28/$C$31,0) -> 0
D29: =IFERROR(C29/$C$31,0) -> 0
D30: =IFERROR(C30/$C$31,0) -> 0
B31: Total | C31: =SUM(C26:C30) -> 473.62 | D31: =SUM(D26:D30) -> 1
B33: Share count bridge
B34: Acquirer shares before | C34: =C22 -> 3157.94
B35: Less: shares held by target, cancelled | C35: =SUMIF(D16:D21,"Y",C16:C21)*-1 -> -1055.75
B36: Add: new shares issued (target shares × ratio) | C36: =C31*C11 -> 2415.462
B37: Shares after merger | C37: =SUM(C34:C36) -> 4517.652
B38: Net increase in share count (dilution) | C38: =IFERROR((C37-C22)/C22,0) -> 0.4305693
B40: Ownership after merger
B41: Holder | C41: Shares after (mn) | D41: % after | E41: Came from
B42: =IF(B16="","",B16) -> SAMIL | C42: =IF(B16="",0,IF(D16="Y",0,C16)) -> 0 | D42: =IFERROR(C42/$C$37,0) -> 0 | E42: =IF(B16="","",IF(D16="Y","Cancelled","Acquirer holder")) -> Cancelled
B43: =IF(B17="","",B17) -> SWS | C43: =IF(B17="",0,IF(D17="Y",0,C17)) -> 800.3 | D43: =IFERROR(C43/$C$37,0) -> 0.17714955 | E43: =IF(B17="","",IF(D17="Y","Cancelled","Acquirer holder")) -> Acquirer holder
B44: =IF(B18="","",B18) -> Family (direct) | C44: =IF(B18="",0,IF(D18="Y",0,C18)) -> 93.24 | D44: =IFERROR(C44/$C$37,0) -> 0.02063904 | E44: =IF(B18="","",IF(D18="Y","Cancelled","Acquirer holder")) -> Acquirer holder
B45: =IF(B19="","",B19) -> Public | C45: =IF(B19="",0,IF(D19="Y",0,C19)) -> 1208.65 | D45: =IFERROR(C45/$C$37,0) -> 0.26753942 | E45: =IF(B19="","",IF(D19="Y","Cancelled","Acquirer holder")) -> Acquirer holder
B46: =IF(B20="","",B20) | C46: =IF(B20="",0,IF(D20="Y",0,C20)) -> 0 | D46: =IFERROR(C46/$C$37,0) -> 0 | E46: =IF(B20="","",IF(D20="Y","Cancelled","Acquirer holder"))
B47: =IF(B21="","",B21) | C47: =IF(B21="",0,IF(D21="Y",0,C21)) -> 0 | D47: =IFERROR(C47/$C$37,0) -> 0 | E47: =IF(B21="","",IF(D21="Y","Cancelled","Acquirer holder"))
B48: =IF(B26="","",B26) -> Family | C48: =C26*$C$11 -> 2183.565 | D48: =IFERROR(C48/$C$37,0) -> 0.48334068 | E48: =IF(B26="","","New shares (target holder)") -> New shares (target holder)
B49: =IF(B27="","",B27) -> Sojitz + staff | C49: =C27*$C$11 -> 231.897 | D49: =IFERROR(C49/$C$37,0) -> 0.051331311 | E49: =IF(B27="","","New shares (target holder)") -> New shares (target holder)
B50: =IF(B28="","",B28) | C50: =C28*$C$11 -> 0 | D50: =IFERROR(C50/$C$37,0) -> 0 | E50: =IF(B28="","","New shares (target holder)")
B51: =IF(B29="","",B29) | C51: =C29*$C$11 -> 0 | D51: =IFERROR(C51/$C$37,0) -> 0 | E51: =IF(B29="","","New shares (target holder)")
B52: =IF(B30="","",B30) | C52: =C30*$C$11 -> 0 | D52: =IFERROR(C52/$C$37,0) -> 0 | E52: =IF(B30="","","New shares (target holder)")
B53: Total | C53: =SUM(C42:C52) -> 4517.652 | D53: =SUM(D42:D52) -> 1
B55: Consolidated by holder (adds up a holder that appears in both companies)
B56: Holder name (type exactly as above) | C56: Shares after (mn) | D56: % after
B57: Family | C57: =SUMIF($B$42:$B$52,B57,$C$42:$C$52) -> 2183.565 | D57: =IFERROR(C57/$C$37,0) -> 0.48334068
B58: Family (direct) | C58: =SUMIF($B$42:$B$52,B58,$C$42:$C$52) -> 93.24 | D58: =IFERROR(C58/$C$37,0) -> 0.02063904
B59: Public | C59: =SUMIF($B$42:$B$52,B59,$C$42:$C$52) -> 1208.65 | D59: =IFERROR(C59/$C$37,0) -> 0.26753942
B60: SWS | C60: =SUMIF($B$42:$B$52,B60,$C$42:$C$52) -> 800.3 | D60: =IFERROR(C60/$C$37,0) -> 0.17714955
B61: Sojitz + staff | C61: =SUMIF($B$42:$B$52,B61,$C$42:$C$52) -> 231.897 | D61: =IFERROR(C61/$C$37,0) -> 0.051331311
B62: Family total (direct + via target) | C62: =C57+C58 -> 2276.805 | D62: =IFERROR(C62/$C$37,0) -> 0.50397972
B64: Fairness check: does value per share change?
B65: Acquirer equity value (₹ cr) = shares × ₹/share ÷ 10 | C65: =C22*C8/10 -> 31929.931
B66: Target equity value (₹ cr) | C66: =C31*C9/10 -> 24440.213
B67: Less: value of cancelled acquirer shares (₹ cr) | C67: =C35*C8/10 -> -10674.688
B68: Merged equity value (₹ cr) | C68: =C65+C66+C67 -> 45695.456
B69: Value per share after (₹) | C69: =IFERROR(C68/C37*10,0) -> 101.14869
B70: Value per share before (₹) | C70: =C8 -> 101.11
B71: Change for continuing holders | C71: =IFERROR(C69/C70-1,0) -> 0.00038260401 | H71: ~0% = fair. Negative = value moved to target holders. Positive = value moved to acquirer holders.
B73: Note: shares (mn) × ₹/share ÷ 10 = ₹ crore.

Sheet Demerger Calc
B2: Demerger Calculator
B3: Prefilled with Motherson Step 1 (DWH into MSWIL, 1:1). Try ITC Hotels: 1 new per 10 parent shares, parent keeps 40%.
B5: Inputs
B6: Parent company | C6: MSSL
B7: Resulting (new) company | C7: MSWIL
B8: New shares issued (numerator) | C8: 1
B9: … for every X parent shares (denominator) | C9: 1
B10: Parent keeps this % of new company | C10: 0 | H10: 0% for Motherson. 40% for ITC Hotels.
B11: Parent share price before ex-date (₹) | C11: 234.8
B12: Value of demerged business per parent share (₹) | C12: 47.2
B14: Parent shareholders
B15: Holder | C15: Parent shares (mn) | D15: % of parent | E15: New co shares (mn) | F15: % of new co (direct) | G15: Look-through % of business
B16: SAMIL | C16: 1055.75 | D16: =IFERROR(C16/$C$22,0) -> 0.33431604 | E16: =C16*$C$8/$C$9 -> 1055.75 | F16: =IFERROR(E16/$E$24,0) -> 0.33431604 | G16: =F16+D16*$F$23 -> 0.33431604 | H16: Look-through = direct stake + (stake in parent × parent's stake in new co). With mirror ownership it equals the % of parent: nobody gains or loses.
B17: SWS | C17: 800.3 | D17: =IFERROR(C17/$C$22,0) -> 0.2534247 | E17: =C17*$C$8/$C$9 -> 800.3 | F17: =IFERROR(E17/$E$24,0) -> 0.2534247 | G17: =F17+D17*$F$23 -> 0.2534247
B18: Family (direct) | C18: 93.24 | D18: =IFERROR(C18/$C$22,0) -> 0.029525577 | E18: =C18*$C$8/$C$9 -> 93.24 | F18: =IFERROR(E18/$E$24,0) -> 0.029525577 | G18: =F18+D18*$F$23 -> 0.029525577
B19: Public | C19: 1208.65 | D19: =IFERROR(C19/$C$22,0) -> 0.38273368 | E19: =C19*$C$8/$C$9 -> 1208.65 | F19: =IFERROR(E19/$E$24,0) -> 0.38273368 | G19: =F19+D19*$F$23 -> 0.38273368
D20: =IFERROR(C20/$C$22,0) -> 0 | E20: =C20*$C$8/$C$9 -> 0 | F20: =IFERROR(E20/$E$24,0) -> 0 | G20: =F20+D20*$F$23 -> 0
D21: =IFERROR(C21/$C$22,0) -> 0 | E21: =C21*$C$8/$C$9 -> 0 | F21: =IFERROR(E21/$E$24,0) -> 0 | G21: =F21+D21*$F$23 -> 0
B22: Total to parent's shareholders | C22: =SUM(C16:C21) -> 3157.94 | D22: =SUM(D16:D21) -> 1 | E22: =SUM(E16:E21) -> 3157.94 | F22: =SUM(F16:F21) -> 1
B23: Parent company itself (retained stake) | E23: =IFERROR(E22*$C$10/(1-$C$10),0) -> 0 | F23: =IFERROR(E23/$E$24,0) -> 0
B24: New company total shares | E24: =E22+E23 -> 3157.94 | F24: =F22+F23 -> 1
B26: Price adjustment on the ex-date
B27: Parent price before (₹) | C27: =C11 -> 234.8
B28: Less: value leaving per parent share (₹) | C28: =-C12 -> -47.2
B29: Expected parent ex-price (₹) | C29: =C27+C28 -> 187.6
B30: Implied price per new co share (₹) | C30: =IFERROR(C12*C9/C8*(1-C10),0) -> 47.2 | H30: For Motherson the market-implied MSWIL value was ~₹47; it listed at ₹66 on 28 Mar 2022.
B31: Check: ex-price + entitlement value = old price (₹) | C31: =C29+C30*C8/C9 -> 234.8

Sheet Motherson Model
B2: Motherson: why the order mattered
B3: Real numbers. Left: what they did (demerge, then merge). Right: the alternative (merge, then demerge). Shares in mn.
B5: Inputs
B6: MSSL shares held by SAMIL | C6: 1055.75
B7: MSSL shares held by SWS (incl. HK Wiring) | C7: 800.3
B8: MSSL shares held by family directly | C8: 93.24
B9: MSSL shares held by public | C9: 1208.65
B10: SAMIL shares outstanding (₹10 face value) | C10: 473.61
B11: Family share of SAMIL | C11: 0.904
B12: Sojitz + staff share of SAMIL | C12: 0.096
B13: Swap ratio, demerge-first (actual) | C13: 5.1
B14: Swap ratio, merge-first (alternative) | C14: 5.1 | H14: If DWH stays inside MSSL, MSSL is worth more per share, so a fair ratio would be ~4.5. Try it.
B15: DWH entitlement (new shares per MSSL share) | C15: 1
B16: MSSL total shares before | C16: =SUM(C6:C9) -> 3157.94
B18: A. Demerge first, then merge (ACTUAL) | F18: B. Merge first, then demerge
B19: Step 1 (A): MSWIL issued to MSSL holders | F19: Step 1 (B): merger
B20: MSWIL holder | C20: Shares | D20: % | F20: Item | G20: Shares
B21: SAMIL | C21: =C6*$C$15 -> 1055.75 | D21: =C21/$C$25 -> 0.33431604 | F21: MSSL shares before | G21: =C16 -> 3157.94
B22: SWS | C22: =C7*$C$15 -> 800.3 | D22: =C22/$C$25 -> 0.2534247 | F22: Cancel SAMIL's MSSL shares | G22: =-C6 -> -1055.75
B23: Family (direct) | C23: =C8*$C$15 -> 93.24 | D23: =C23/$C$25 -> 0.029525577 | F23: New shares to SAMIL holders | G23: =C10*C14 -> 2415.411
B24: Public | C24: =C9*$C$15 -> 1208.65 | D24: =C24/$C$25 -> 0.38273368 | F24: Merged shares | G24: =SUM(G21:G23) -> 4517.601
B25: Total MSWIL shares | C25: =SUM(C21:C24) -> 3157.94
B27: Step 2 (A): merger of SAMIL into MSSL ex-DWH | F27: Step 2 (B): MSWIL mirrors merged MSSL
B28: MSSL shares before | C28: =C16 -> 3157.94
B29: Cancel SAMIL's MSSL shares | C29: =-C6 -> -1055.75
B30: New shares to SAMIL holders | C30: =C10*C13 -> 2415.411
B31: Merged shares | C31: =SUM(C28:C30) -> 4517.601
B33: Result: ownership of the main listed company (Motherson)
B34: Holder | C34: A: shares | D34: A: % | F34: B: shares | G34: B: %
B35: Family | C35: =C8+C11*C30 -> 2276.7715 | D35: =C35/$C$31 -> 0.50397801 | F35: =C8+C11*G23 -> 2276.7715 | G35: =F35/$G$24 -> 0.50397801
B36: SWS | C36: =C7 -> 800.3 | D36: =C36/$C$31 -> 0.17715155 | F36: =C7 -> 800.3 | G36: =F36/$G$24 -> 0.17715155
B37: Public | C37: =C9 -> 1208.65 | D37: =C37/$C$31 -> 0.26754244 | F37: =C9 -> 1208.65 | G37: =F37/$G$24 -> 0.26754244
B38: Sojitz + staff | C38: =C12*C30 -> 231.87946 | D38: =C38/$C$31 -> 0.051328007 | F38: =C12*G23 -> 231.87946 | G38: =F38/$G$24 -> 0.051328007
B39: Total | C39: =SUM(C35:C38) -> 4517.601 | D39: =SUM(D35:D38) -> 1 | F39: =SUM(F35:F38) -> 4517.601 | G39: =SUM(G35:G38) -> 1
B41: Result: ownership of the wiring company (MSWIL)
B42: Holder | C42: A: % | E42: B: %
B43: SWS | C43: =D22 -> 0.2534247 | E43: =G36 -> 0.17715155
B44: Public | C44: =D24 -> 0.38273368 | E44: =G37 -> 0.26754244
B45: Family (direct) | C45: =D23 -> 0.029525577 | E45: =G35 -> 0.50397801
B46: Motherson (listed parent) | C46: =D21 -> 0.33431604 | E46: =0 -> 0
B47: Sojitz + staff | C47: =0 -> 0 | E47: =G38 -> 0.051328007
B48: Total | C48: =SUM(C43:C47) -> 1 | E48: =SUM(E43:E47) -> 1
B49: In A, Motherson's 33.4% is SAMIL's MSWIL stake that moved in with the merger.
B51: Look-through: each party's real share of the Indian wiring business
B52: Party | C52: A (actual) | E52: B (alternative) | G52: So what
B53: SWS | C53: =C43+D36*C46 -> 0.3126493 | E53: =E43 -> 0.17715155 | G53: SWS keeps more of the business it wanted in A
B54: Family | C54: =C45+D35*C46 -> 0.19801351 | E54: =E45 -> 0.50397801 | G54: Family gets far more DWH directly in B
B55: Public (old MSSL holders) | C55: =C44+D37*C46 -> 0.47217741 | E55: =E44 -> 0.26754244 | G55: Public owns more DWH in A

Sheet Practice
B2: Practice Problems
B3: Type your answer in the YELLOW cell. Percentages: type 48% (or 0.48). The Check column turns to Correct within 0.5%. Hints on the right; full workings on the Solutions sheet.
B4: Tip: change the blue inputs on the Solutions sheet to generate fresh variants of every problem.
B6: P1 | C6: Simple merger
C7: Acquirer: 1,000 mn shares (Promoter A 600, Public A 400), worth ₹200/share. Target: 500 mn shares (Promoter T 300, Public T 200), worth ₹100/share. Share-swap merger, no cross-holdings.
C8: Question | E8: Your answer | F8: Check | G8: Hint
C9: Swap ratio | E9: 0.5 | F9: =IF(E9="","",IF(ABS(E9-Solutions!D14)<=MAX(0.005*ABS(Solutions!D14),0.0005),"Correct","Try again")) -> Correct | G9: Ratio = 100 ÷ 200. Total shares = 1,000 + new shares.
C10: New shares issued (mn) | F10: =IF(E10="","",IF(ABS(E10-Solutions!D15)<=MAX(0.005*ABS(Solutions!D15),0.0005),"Correct","Try again")) | G10: Example: the swap-ratio answer (0.5) is filled in to show the format.
C11: Total shares after (mn) | F11: =IF(E11="","",IF(ABS(E11-Solutions!D16)<=MAX(0.005*ABS(Solutions!D16),0.0005),"Correct","Try again"))
C12: Promoter A % after | F12: =IF(E12="","",IF(ABS(E12-Solutions!D17)<=MAX(0.005*ABS(Solutions!D17),0.0005),"Correct","Try again"))
C13: Public A % after | F13: =IF(E13="","",IF(ABS(E13-Solutions!D18)<=MAX(0.005*ABS(Solutions!D18),0.0005),"Correct","Try again"))
C14: Promoter T % after | F14: =IF(E14="","",IF(ABS(E14-Solutions!D19)<=MAX(0.005*ABS(Solutions!D19),0.0005),"Correct","Try again"))
C15: Public T % after | F15: =IF(E15="","",IF(ABS(E15-Solutions!D20)<=MAX(0.005*ABS(Solutions!D20),0.0005),"Correct","Try again"))
B17: P2 | C17: Promoter holdco merger
C18: ListCo: 1,000 mn shares (HoldCo 400, Public 600), worth ₹50/share. HoldCo: 100 mn shares, 100% owned by Promoter. HoldCo holds its 400 ListCo shares plus other assets of ₹10,000 mn and net debt of ₹2,000 mn. HoldCo merges into ListCo.
C19: Question | E19: Your answer | F19: Check | G19: Hint
C20: HoldCo equity value (₹ mn) | F20: =IF(E20="","",IF(ABS(E20-Solutions!D30)<=MAX(0.005*ABS(Solutions!D30),0.0005),"Correct","Try again")) | G20: HoldCo value = 400 × 50 + 10,000 − 2,000. Cancel HoldCo's 400 ListCo shares.
C21: HoldCo value per share (₹) | F21: =IF(E21="","",IF(ABS(E21-Solutions!D31)<=MAX(0.005*ABS(Solutions!D31),0.0005),"Correct","Try again"))
C22: Swap ratio | F22: =IF(E22="","",IF(ABS(E22-Solutions!D32)<=MAX(0.005*ABS(Solutions!D32),0.0005),"Correct","Try again"))
C23: New ListCo shares issued (mn) | F23: =IF(E23="","",IF(ABS(E23-Solutions!D33)<=MAX(0.005*ABS(Solutions!D33),0.0005),"Correct","Try again"))
C24: Shares cancelled (mn) | F24: =IF(E24="","",IF(ABS(E24-Solutions!D34)<=MAX(0.005*ABS(Solutions!D34),0.0005),"Correct","Try again"))
C25: Total ListCo shares after (mn) | F25: =IF(E25="","",IF(ABS(E25-Solutions!D35)<=MAX(0.005*ABS(Solutions!D35),0.0005),"Correct","Try again"))
C26: Promoter % after | F26: =IF(E26="","",IF(ABS(E26-Solutions!D36)<=MAX(0.005*ABS(Solutions!D36),0.0005),"Correct","Try again"))
C27: Public % after | F27: =IF(E27="","",IF(ABS(E27-Solutions!D37)<=MAX(0.005*ABS(Solutions!D37),0.0005),"Correct","Try again"))
C28: Value per share after (₹) | F28: =IF(E28="","",IF(ABS(E28-Solutions!D38)<=MAX(0.005*ABS(Solutions!D38),0.0005),"Correct","Try again"))
B30: P3 | C30: Mirror demerger
C31: Parent: 2,000 mn shares (Promoter 1,000, FIIs 400, Public 600). Demerger ratio: 1 new share for every 4 parent shares.
C32: Question | E32: Your answer | F32: Check | G32: Hint
C33: New company total shares (mn) | F33: =IF(E33="","",IF(ABS(E33-Solutions!D47)<=MAX(0.005*ABS(Solutions!D47),0.0005),"Correct","Try again")) | G33: Each holder gets parent shares ÷ 4.
C34: Promoter shares in new co (mn) | F34: =IF(E34="","",IF(ABS(E34-Solutions!D48)<=MAX(0.005*ABS(Solutions!D48),0.0005),"Correct","Try again"))
C35: Promoter % of new co | F35: =IF(E35="","",IF(ABS(E35-Solutions!D49)<=MAX(0.005*ABS(Solutions!D49),0.0005),"Correct","Try again"))
C36: FII % of new co | F36: =IF(E36="","",IF(ABS(E36-Solutions!D50)<=MAX(0.005*ABS(Solutions!D50),0.0005),"Correct","Try again"))
C37: Public % of new co | F37: =IF(E37="","",IF(ABS(E37-Solutions!D51)<=MAX(0.005*ABS(Solutions!D51),0.0005),"Correct","Try again"))
B39: P4 | C39: Demerger with retained stake
C40: Parent: 1,000 mn shares (Institutions 700, Retail 300). Ratio: 1 new share per 10 parent shares. The parent itself keeps 40% of the new company (holders get 60%).
C41: Question | E41: Your answer | F41: Check | G41: Hint
C42: New co shares issued to parent's holders (mn) | F42: =IF(E42="","",IF(ABS(E42-Solutions!D60)<=MAX(0.005*ABS(Solutions!D60),0.0005),"Correct","Try again")) | G42: Total new co shares = shares to holders ÷ 60%.
C43: New co total shares (mn) | F43: =IF(E43="","",IF(ABS(E43-Solutions!D61)<=MAX(0.005*ABS(Solutions!D61),0.0005),"Correct","Try again"))
C44: Parent's new co shares (mn) | F44: =IF(E44="","",IF(ABS(E44-Solutions!D62)<=MAX(0.005*ABS(Solutions!D62),0.0005),"Correct","Try again"))
C45: Institutions direct % of new co | F45: =IF(E45="","",IF(ABS(E45-Solutions!D63)<=MAX(0.005*ABS(Solutions!D63),0.0005),"Correct","Try again"))
C46: Institutions look-through % of new co | F46: =IF(E46="","",IF(ABS(E46-Solutions!D64)<=MAX(0.005*ABS(Solutions!D64),0.0005),"Correct","Try again"))
B48: P5 | C48: Ex-date price
C49: Parent trades at ₹500. The demerged business is worth ₹120 per parent share. Ratio 1:1. The new company lists at ₹150.
C50: Question | E50: Your answer | F50: Check | G50: Hint
C51: Expected parent ex-price (₹) | F51: =IF(E51="","",IF(ABS(E51-Solutions!D71)<=MAX(0.005*ABS(Solutions!D71),0.0005),"Correct","Try again")) | G51: Ex-price = 500 − 120.
C52: Holder's value after listing (₹ per original share) | F52: =IF(E52="","",IF(ABS(E52-Solutions!D72)<=MAX(0.005*ABS(Solutions!D72),0.0005),"Correct","Try again"))
C53: Gain vs before (%) | F53: =IF(E53="","",IF(ABS(E53-Solutions!D73)<=MAX(0.005*ABS(Solutions!D73),0.0005),"Correct","Try again"))
B55: P6 | C55: Motherson actual
C56: MSSL: 3,157.93 mn shares; SAMIL holds 1,055.75 mn; family holds 93.24 mn directly. SAMIL: 473.61 mn shares, 90.4% family. Ratio 5.1.
C57: Question | E57: Your answer | F57: Check | G57: Hint
C58: New shares issued (mn) | F58: =IF(E58="","",IF(ABS(E58-Solutions!D82)<=MAX(0.005*ABS(Solutions!D82),0.0005),"Correct","Try again")) | G58: New = 473.61 × 5.1. Cancel SAMIL's MSSL shares.
C59: Merged shares (mn) | F59: =IF(E59="","",IF(ABS(E59-Solutions!D83)<=MAX(0.005*ABS(Solutions!D83),0.0005),"Correct","Try again"))
C60: Family % after | F60: =IF(E60="","",IF(ABS(E60-Solutions!D84)<=MAX(0.005*ABS(Solutions!D84),0.0005),"Correct","Try again"))
B62: P7 | C62: Order matters
C63: MSSL: 100 shares (SAMIL 33, Public 39, SWS 25, Family 3). SAMIL's other assets are worth 43 MSSL shares. Family owns 90% of SAMIL. Compare SWS's stake in the wiring company under each order.
C64: Question | E64: Your answer | F64: Check | G64: Hint
C65: New shares to SAMIL holders | F65: =IF(E65="","",IF(ABS(E65-Solutions!D94)<=MAX(0.005*ABS(Solutions!D94),0.0005),"Correct","Try again")) | G65: SAMIL is worth 33 + 43 MSSL shares.
C66: Merged shares | F66: =IF(E66="","",IF(ABS(E66-Solutions!D95)<=MAX(0.005*ABS(Solutions!D95),0.0005),"Correct","Try again"))
C67: Family % after merger | F67: =IF(E67="","",IF(ABS(E67-Solutions!D96)<=MAX(0.005*ABS(Solutions!D96),0.0005),"Correct","Try again"))
C68: SWS % of wiring co if MERGE first | F68: =IF(E68="","",IF(ABS(E68-Solutions!D97)<=MAX(0.005*ABS(Solutions!D97),0.0005),"Correct","Try again"))
C69: SWS % of wiring co if DEMERGE first | F69: =IF(E69="","",IF(ABS(E69-Solutions!D98)<=MAX(0.005*ABS(Solutions!D98),0.0005),"Correct","Try again"))
B71: P8 | C71: Value leakage
C72: Same as P2 (HoldCo equity worth ₹28,000 mn), but the board agrees a ratio of 6.5 instead of the fair 5.6.
C73: Question | E73: Your answer | F73: Check | G73: Hint
C74: Total shares after (mn) | F74: =IF(E74="","",IF(ABS(E74-Solutions!D108)<=MAX(0.005*ABS(Solutions!D108),0.0005),"Correct","Try again")) | G74: Value per share after = (50,000 + 28,000 − 20,000) ÷ total shares.
C75: Value per share after (₹) | F75: =IF(E75="","",IF(ABS(E75-Solutions!D109)<=MAX(0.005*ABS(Solutions!D109),0.0005),"Correct","Try again"))
C76: Public value before (₹ mn) | F76: =IF(E76="","",IF(ABS(E76-Solutions!D110)<=MAX(0.005*ABS(Solutions!D110),0.0005),"Correct","Try again"))
C77: Public value after (₹ mn) | F77: =IF(E77="","",IF(ABS(E77-Solutions!D111)<=MAX(0.005*ABS(Solutions!D111),0.0005),"Correct","Try again"))
C78: Public gain / (loss) (₹ mn) | F78: =IF(E78="","",IF(ABS(E78-Solutions!D112)<=MAX(0.005*ABS(Solutions!D112),0.0005),"Correct","Try again"))
B80: P9 | C80: EPS accretion
C81: Acquirer PAT ₹537 cr on 3,157.9 mn shares. After the merger: PAT ₹830 cr on 4,517.6 mn shares.
C82: Question | E82: Your answer | F82: Check | G82: Hint
C83: EPS before (₹) | F83: =IF(E83="","",IF(ABS(E83-Solutions!D119)<=MAX(0.005*ABS(Solutions!D119),0.0005),"Correct","Try again")) | G83: EPS = ₹ cr ÷ mn shares × 10.
C84: EPS after (₹) | F84: =IF(E84="","",IF(ABS(E84-Solutions!D120)<=MAX(0.005*ABS(Solutions!D120),0.0005),"Correct","Try again"))
C85: Accretion / (dilution) | F85: =IF(E85="","",IF(ABS(E85-Solutions!D121)<=MAX(0.005*ABS(Solutions!D121),0.0005),"Correct","Try again"))
B87: P10 | C87: Vote tests
C88: Votes FOR 2,700 mn shares, AGAINST 60 mn. Of these, public FOR 760 mn, public AGAINST 4.3 mn.
C89: Question | E89: Your answer | F89: Check | G89: Hint
C90: % FOR by value (needs ≥ 75%) | F90: =IF(E90="","",IF(ABS(E90-Solutions!D128)<=MAX(0.005*ABS(Solutions!D128),0.0005),"Correct","Try again")) | G90: Three-fourths by value; public FOR must exceed public AGAINST.
C91: Public % FOR (needs > 50%) | F91: =IF(E91="","",IF(ABS(E91-Solutions!D129)<=MAX(0.005*ABS(Solutions!D129),0.0005),"Correct","Try again"))
C92: Passes both? (1 = yes, 0 = no) | F92: =IF(E92="","",IF(ABS(E92-Solutions!D130)<=MAX(0.005*ABS(Solutions!D130),0.0005),"Correct","Try again"))
B94: P11 | C94: Look-through
C95: Public held 38.27% of MSSL, which held 51% of SMRP BV. After the merger the public holds 26.75% of a company that owns 100% of SMRP BV.
C96: Question | E96: Your answer | F96: Check | G96: Hint
C97: Public look-through in SMRP BV before | F97: =IF(E97="","",IF(ABS(E97-Solutions!D137)<=MAX(0.005*ABS(Solutions!D137),0.0005),"Correct","Try again")) | G97: Multiply stakes along the chain.
C98: Public look-through in SMRP BV after | F98: =IF(E98="","",IF(ABS(E98-Solutions!D138)<=MAX(0.005*ABS(Solutions!D138),0.0005),"Correct","Try again"))
C99: Change (percentage points) | F99: =IF(E99="","",IF(ABS(E99-Solutions!D139)<=MAX(0.005*ABS(Solutions!D139),0.0005),"Correct","Try again"))
C101: Score | E101: =COUNTIF(F6:F100,"Correct") -> 1 | F101: ="of "&SUMPRODUCT(--(E6:E100<>""))&" attempted" -> of 12 attempted

Sheet Solutions
B2: Solutions (worked with formulas)
B3: Problem inputs are blue. Change them to create new practice variants. Practice sheet checks against these answers.
B5: P1 | C5: Simple merger
C6: Acquirer shares (mn) | D6: 1000
C7: of which Promoter A | D7: 600
C8: of which Public A | D8: 400
C9: Acquirer value per share (₹) | D9: 200
C10: Target shares (mn) | D10: 500
C11: of which Promoter T | D11: 300
C12: of which Public T | D12: 200
C13: Target value per share (₹) | D13: 100
C14: Swap ratio | D14: =D13/D9 -> 0.5 | E14: Target ₹/share ÷ acquirer ₹/share
C15: New shares issued (mn) | D15: =D10*D14 -> 250 | E15: Target shares × ratio
C16: Total shares after (mn) | D16: =D6+D15 -> 1250 | E16: No cross-holding to cancel
C17: Promoter A % after | D17: =D7/D16 -> 0.48
C18: Public A % after | D18: =D8/D16 -> 0.32
C19: Promoter T % after | D19: =D11*D14/D16 -> 0.12
C20: Public T % after | D20: =D12*D14/D16 -> 0.08
B22: P2 | C22: Promoter holdco merger with cancellation (Motherson-style)
C23: ListCo shares (mn) | D23: 1000
C24: held by HoldCo | D24: 400
C25: held by Public | D25: 600
C26: ListCo value per share (₹) | D26: 50
C27: HoldCo shares (mn), 100% owned by Promoter | D27: 100
C28: HoldCo other assets (₹ mn) | D28: 10000
C29: HoldCo net debt (₹ mn) | D29: 2000
C30: HoldCo equity value (₹ mn) | D30: =D24*D26+D28-D29 -> 28000 | E30: Its ListCo shares + other assets − debt
C31: HoldCo value per share (₹) | D31: =D30/D27 -> 280
C32: Swap ratio | D32: =D31/D26 -> 5.6 | E32: HoldCo ₹/share ÷ ListCo ₹/share
C33: New ListCo shares issued (mn) | D33: =D27*D32 -> 560
C34: Shares cancelled (mn) | D34: =D24 -> 400 | E34: HoldCo's own ListCo shares
C35: Total ListCo shares after (mn) | D35: =D23-D34+D33 -> 1160
C36: Promoter % after | D36: =D33/D35 -> 0.48275862 | E36: Promoter owned 100% of HoldCo
C37: Public % after | D37: =D25/D35 -> 0.51724138
C38: Value per share after (₹) | D38: =(D23*D26+D28-D29)/D35 -> 50 | E38: Unchanged = fair
B40: P3 | C40: Mirror demerger (1 new for every 4)
C41: Parent shares (mn) | D41: 2000
C42: Promoter | D42: 1000
C43: FIIs | D43: 400
C44: Public | D44: 600
C45: New shares (numerator) | D45: 1
C46: … per parent shares (denominator) | D46: 4
C47: New company total shares (mn) | D47: =D41*D45/D46 -> 500
C48: Promoter shares in new co (mn) | D48: =D42*D45/D46 -> 250
C49: Promoter % of new co | D49: =D48/D47 -> 0.5 | E49: Same as % of parent
C50: FII % of new co | D50: =D43*D45/D46/D47 -> 0.2
C51: Public % of new co | D51: =D44*D45/D46/D47 -> 0.3
B53: P4 | C53: Demerger where parent keeps 40% (ITC Hotels-style)
C54: Parent shares (mn) | D54: 1000
C55: Institutions | D55: 700
C56: Retail | D56: 300
C57: New shares (numerator) | D57: 1
C58: … per parent shares (denominator) | D58: 10
C59: Parent retains % of new co | D59: 0.4
C60: New co shares issued to parent's holders (mn) | D60: =D54*D57/D58 -> 100
C61: New co total shares (mn) | D61: =D60/(1-D59) -> 166.66667 | E61: Holders get 60%, so total = holders ÷ 60%
C62: Parent's new co shares (mn) | D62: =D61*D59 -> 66.666667
C63: Institutions direct % of new co | D63: =D55*D57/D58/D61 -> 0.42
C64: Institutions look-through % of new co | D64: =D63+D55/D54*D59 -> 0.7 | E64: Direct + 70% × parent's 40% = 70% (unchanged)
B66: P5 | C66: Ex-date price maths
C67: Parent price before ex-date (₹) | D67: 500
C68: Demerged business value per parent share (₹) | D68: 120
C69: New shares per parent share | D69: 1
C70: New co listing price (₹) | D70: 150
C71: Expected parent ex-price (₹) | D71: =D67-D68 -> 380
C72: Holder's value after listing (₹ per original share) | D72: =D71+D70*D69 -> 530 | E72: Parent ex-price + new co shares × listing price
C73: Gain vs before (%) | D73: =D72/D67-1 -> 0.06
B75: P6 | C75: Motherson actual: post-merger family stake
C76: MSSL shares (mn) | D76: 3157.93
C77: SAMIL's MSSL shares (mn) | D77: 1055.75
C78: Family direct MSSL shares (mn) | D78: 93.24
C79: SAMIL shares (mn) | D79: 473.61
C80: Swap ratio | D80: 5.1
C81: Family share of SAMIL | D81: 0.904
C82: New shares issued (mn) | D82: =D79*D80 -> 2415.411
C83: Merged shares (mn) | D83: =D76-D77+D82 -> 4517.591 | E83: Expected 4,517.6
C84: Family % after | D84: =(D78+D81*D82)/D83 -> 0.50397912 | E84: Expected ~50.4%
B86: P7 | C86: Order matters (100-share toy)
C87: MSSL shares | D87: 100
C88: held by SAMIL | D88: 33
C89: Public | D89: 39
C90: SWS | D90: 25
C91: Family direct | D91: 3
C92: SAMIL other assets, in MSSL-share equivalents | D92: 43
C93: Family share of SAMIL | D93: 0.9
C94: New shares to SAMIL holders | D94: =D88+D92 -> 76 | E94: SAMIL worth 33 + 43 = 76 MSSL shares
C95: Merged shares | D95: =D87-D88+D94 -> 143
C96: Family % after merger | D96: =(D91+D93*D94)/D95 -> 0.4993007
C97: SWS % of wiring co if MERGE first | D97: =D90/D95 -> 0.17482517 | E97: Wiring co mirrors merged company
C98: SWS % of wiring co if DEMERGE first | D98: =D90/D87 -> 0.25 | E98: Wiring co mirrors old MSSL
B100: P8 | C100: Value leakage when the ratio is too high (use P2 numbers)
C101: ListCo shares (mn) | D101: 1000
C102: held by HoldCo | D102: 400
C103: held by Public | D103: 600
C104: ListCo value per share (₹) | D104: 50
C105: HoldCo shares (mn) | D105: 100
C106: HoldCo equity value (₹ mn) | D106: 28000
C107: Ratio actually agreed | D107: 6.5
C108: Total shares after (mn) | D108: =D101-D102+D105*D107 -> 1250
C109: Value per share after (₹) | D109: =(D101*D104+D106-D102*D104)/D108 -> 46.4 | E109: Merged value ÷ shares
...
